elifetools/__init__.py
elifetools/json_rewrite.py
elifetools/parseJATS.py
elifetools/rawJATS.py
elifetools/utils.py
elifetools/utils_html.py
elifetools/xmlio.py
elifetools-0.48.0.dist-info/LICENSE
elifetools-0.48.0.dist-info/METADATA
elifetools-0.48.0.dist-info/WHEEL
elifetools-0.48.0.dist-info/top_level.txt
elifetools-0.48.0.dist-info/RECORD
