Metadata-Version: 2.1
Name: elifetools
Version: 0.48.0
Summary: Tools for using article data in Python.
Home-page: https://github.com/elifesciences/elife-tools
Maintainer: eLife Sciences Publications Ltd.
Maintainer-email: tech-team@elifesciences.org
License: MIT
Classifier: Development Status :: 3 - Alpha
Classifier: Intended Audience :: Developers
Classifier: License :: OSI Approved :: MIT License
Classifier: Programming Language :: Python :: 3
License-File: LICENSE
Requires-Dist: beautifulsoup4
Requires-Dist: lxml
Requires-Dist: python-slugify
